futureagi_mcp_server/__init__.py
futureagi_mcp_server/constants.py
futureagi_mcp_server/logger.py
futureagi_mcp_server/server.py
futureagi_mcp_server/utils.py
futureagi_mcp_server/tools/__init__.py
futureagi_mcp_server/tools/datasets.py
futureagi_mcp_server/tools/evals.py
futureagi_mcp_server/tools/prompt.py
futureagi_mcp_server/tools/protect.py
futureagi_mcp_server/tools/routes.py
futureagi_mcp_server/tools/syntheticdatagen.py
futureagi_mcp_server-0.1.0.dist-info/METADATA
futureagi_mcp_server-0.1.0.dist-info/WHEEL
futureagi_mcp_server-0.1.0.dist-info/entry_points.txt
futureagi_mcp_server-0.1.0.dist-info/RECORD
