Metadata-Version: 2.4
Name: futureagi-mcp-server
Version: 0.1.0
Summary: Future AGI MCP Server
Requires-Python: >=3.10
Requires-Dist: futureagi>=0.5.10
Requires-Dist: httpx>=0.28.1
Requires-Dist: mcp[cli]>=1.6.0
Requires-Dist: pydantic>=2.11.2
Provides-Extra: dev
Requires-Dist: pre-commit>=3.6.0; extra == 'dev'
Requires-Dist: pytest-asyncio>=0.23.0; extra == 'dev'
Requires-Dist: pytest-cov>=4.1.0; extra == 'dev'
Requires-Dist: pytest>=8.0.0; extra == 'dev'
Requires-Dist: respx>=0.20.2; extra == 'dev'
